andar/__init__.py
andar/check_utils.py
andar/field_conf.py
andar/parser_utils.py
andar/path_model.py
andar-0.1.10.dist-info/licenses/LICENSE
andar-0.1.10.dist-info/METADATA
andar-0.1.10.dist-info/WHEEL
andar-0.1.10.dist-info/top_level.txt
andar-0.1.10.dist-info/RECORD
