Metadata-Version: 2.4
Name: andar
Version: 0.1.10
Summary: Provides an abstraction layer for creating and parsing paths in a programmatic way via templates.
Project-URL: repository, https://github.com/fabarca/andar
Project-URL: issues, https://github.com/fabarca/andar/issues
Project-URL: documentation, https://fabarca.github.io/andar
Classifier: Intended Audience :: Developers
Classifier: Intended Audience :: Information Technology
Classifier: Programming Language :: Python
Classifier: Topic :: Software Development :: Code Generators
Classifier: Topic :: Software Development :: Libraries :: Python Modules
Classifier: Topic :: System :: Archiving
Classifier: Topic :: Utilities
Requires-Python: >=3.11
License-File: LICENSE
Dynamic: license-file
